{
  "common_0310_rival_01": "Oh yeah—battling can wait. I meant to tell you...\\c\nDid you know your phone’s map app lets you set\nyourself destinations?[VAR 0114(0004)]",
  "common_0310_rival_02": "You could try setting one of the Gyms as your\ndestination! That’d get you on your way easy![VAR 0114(0004)]",
  "common_0310_friend_01": "Tch! How’s that for a student council president!\nGiving your own friends an insider advantage?[VAR 0114(0006)]",
  "common_0310_rival_03": "Ay! A-Arven?![VAR 0114(0004)]",
  "common_0310_rival_04": "[VAR BD06(0000)]Insider advantage? Sheesh, you make it sound\nlike we’re cheating or something!\\c\nAll I did was suggest that [VAR GENDBR(00FF,0100)]she check out the\nGyms. It’s up to [VAR TRNAME(0000)]\\r\nwhether\\r\n[VAR GENDBR(00FF,0100)]she goes.[VAR 0114(0004)]",
  "common_0310_friend_02": "[VAR BD06(0000)][VAR TRNAME(0000)]’s gonna have h[VAR GENDBR(00FF,0202)]iser\nhands\\r\nfull\\r\nsearching\\r\nout\\r\nTitan\\r\nPokémon\\r\nwith me.\\c\n[VAR GENDBR(00FF,0201)]HShe doesn’t have time to waste on something like\nchasing after the Champion Rank.[VAR 0114(0006)]",
  "common_0310_friend_03": "Me and h[VAR GENDBR(00FF,0202)]imer are gonna be too busy visiting the\nlairs of Titans and nabbing their Herba Mystica![VAR 0114(0006)]",
  "common_0310_rival_05": "En serio? Don’t go filling h[VAR GENDBR(00FF,0202)]iser head with\nweird stories![VAR 0114(0004)]",
  "common_0310_friend_04": "Hey! All I did was invite h[VAR GENDBR(00FF,0202)]imer along. It’s still up to\n[VAR TRNAME(0000)] whether [VAR GENDBR(00FF,0100)]she goes, right?[VAR 0114(0006)]",
  "common_0310_rival_06": "Grrr![VAR 0114(0004)]",
  "common_0310_system_01": "Ro-to-to-to-to... ♪",
  "common_0310_friend_05": "[VAR BD06(0000)]Hm? [VAR TRNAME(0000)], your phone’s\nringing.[VAR 0114(0006)]",
  "common_0310_botan_01": "Hey, [VAR TRNAME(0000)]. Cassiopeia here.[VAR 0114(0009)]",
  "common_0310_botan_02": "It’s about Operation Starfall. Remember what\nI told you before?[VAR 0114(0009)]",
  "common_0310_botan_03": "Team Star is made up of five individual squads.\nAnd each one’s got their own base.[VAR 0114(0009)]",
  "common_0310_botan_04": "I need you to go to each base—all five of ’em—\nand beat the squad boss there.[VAR 0114(0009)]",
  "common_0310_botan_05": "Team Star’s grunts might try to get in your way,\nbut I’ll be helping you out...from a distance.[VAR 0114(0009)]",
  "common_0310_botan_06": "And heads-up that the bosses each specialize in\na different Pokémon type. Just remember the\\r\nnames of their crews, and you’ll figure it out.\\c\nStill, no need to worry. With your skills, I’m sure\nyou’re more than up to the task.[VAR 0114(0009)]",
  "common_0310_botan_07": "I’ll just go ahead and add the bases’ locations to\nyour phone for you.[VAR 0114(0009)]",
  "common_0310_botan_08": "Good luck with those bosses. I’ll hook you up\nwith some nice rewards every time you beat one.[VAR 0114(0009)]",
  "common_0310_rival_07": "[VAR BD06(0000)]Wait one second! Who are you supposed to be?!\nAnd Team Star—those punks are a serious hazard!\\r\nThey’re not [VAR TRNAME(0000)]’s\\r\nproblem![VAR 0114(0004)]",
  "common_0310_friend_06": "That’s right! Because [VAR GENDBR(00FF,0100)]she’s got more important\nthings to do, like searching out awesome\\r\ningredients with me![VAR 0114(0006)]",
  "common_0310_botan_09": "[VAR BD06(0000)]I thought it was up to [VAR TRNAME(0000)]\nto\\r\ndecide\\r\nwhether\\r\n[VAR GENDBR(00FF,0100)]she\\r\ngoes\\r\nor not...\\r\nWasn’t\\r\nthat\\r\nwhat\\r\nyou\\r\nsaid,\\r\nNemona?\\r\nAnd Arven?[VAR 0114(0009)]",
  "common_0310_rival_08": "How do you know my—?[VAR 0114(0004)]",
  "common_0310_botan_10": "I’m looking forward to seeing what you can pull\noff, [VAR TRNAME(0000)]. Bye.[VAR 0114(0009)]",
  "common_0310_friend_07": "What was that all about?[VAR 0114(0006)]",
  "common_0310_rival_09": "[VAR BD06(0000)][VAR TRNAME(0000)]... I’m glad you’re\nmaking\\r\nplenty\\r\nof\\r\nfriends\\r\nhere,\\r\nbut\\r\ntry\\r\nnot\\r\nto\\r\nget\\r\ndragged\\r\ninto\\r\nanything\\r\ndangerous.[VAR 0114(0004)]",
  "common_0310_rival_10": "Anyway! No more weird vibes—we’ve got a big\nadventure to start![VAR 0114(0004)]",
  "common_0310_rival_11": "I’m gonna battle every single Pokémon Trainer\nI meet![VAR 0114(0004)]",
  "common_0310_rival_12": "If I just keep trying to become the strongest,\nI bet that experience will be the thing I treasure![VAR 0114(0004)]",
  "common_0310_rival_13": "Guess I’ll start by heading to a Gym and training\nup some new Pokémon! Here, I’ll send you a pic\\r\nof what the Gym buildings look like![VAR 0114(0004)]",
  "common_0310_rival_14": "Oh, and...\\c\nI know we’ve been running our mouths, but it’s\nyour call what you do, [VAR TRNAME(0000)].\\c\nGo where you want, and do what it is you really\nwanna do the most![VAR 0114(0004)]",
  "common_0310_rival_15": "[~ 32]",
  "common_0310_friend_08": "A treasure...of our very own...[VAR 0114(0006)]",
  "common_0310_friend_09": "For me, that’s got to be Ma— Er, my big dream\nof tracking down the Herba Mystica, that is![VAR 0114(0006)]",
  "common_0310_friend_11": "Once we get those herbs, I’ll make you the\nabsoluuute best sandwich you’ve had in your life![VAR 0114(0006)]",
  "common_0310_legend_01": "Agias!",
  "common_0310_friend_12": "Argh! What’d you come out for?[VAR 0114(0006)]",
  "common_0310_rival_16": "Oh my gosh! Did it just come out ’cause you said\n“sandwich”? Hahaha![VAR 0114(0004)]",
  "common_0310_friend_13": "Well, you’re not getting one...[VAR 0114(0006)]",
  "common_0310_legend_02": "Gias! Gias!",
  "common_0310_rival_17": "It seems like it wants to start moving... Is it telling\nyou to get on, [VAR TRNAME(0000)]?[VAR 0114(0004)]",
  "common_0310_system_02": "[~ 42]",
  "common_0310_legend_03": "An-giaaah!",
  "common_0310_rival_18": "Whoa, it transformed! Now it REALLY looks like\nsome kinda weird Cyclizar![VAR 0114(0004)]",
  "common_0310_rival_19": "Long as you’ve got [VAR PKNAME(0001)], you can go\npretty much anywhere. Paldea’s your Cloyster![VAR 0114(0004)]",
  "common_0310_friend_14": "Hmph... Yeah? Maybe.[VAR 0114(0006)]",
  "common_0310_friend_15": "Well, if you’re going to search for those Titan\nPokémon, I’d say set out from the east gate![VAR 0114(0006)]",
  "common_0310_rival_21": "[VAR BD06(0000)]But since [VAR TRNAME(0000)] is ACTUALLY\nheaded\\r\nto\\r\ntake\\r\non\\r\nsome\\r\nGyms,\\r\nI’d\\r\nsay\\r\ngo\\r\nfor\\r\nthe\\r\nwest gate!\\c\nBesides, it’s way too easy to get lost out east![VAR 0114(0004)]",
  "common_0310_friend_10": "Tch! Man, this is why I can’t get along with you...\nI’m out of here! Catch up soon, little buddy![VAR 0114(0006)]",
  "common_0310_rival_20": "[VAR BD06(0000)]I’ll head to a Gym. See you around,\n[VAR TRNAME(0000)]![VAR 0114(0004)]"
}