{
  "common_1180_kari_01": "[~ 0]",
  "common_1180_rival_00": "We’re surrounded![VAR 0114(0004)]",
  "common_1180_friend_18": "And it’s pretty obvious they’re not here to roll\nout a friendly welcome mat.[VAR 0114(0006)]",
  "common_1180_botan_01": "There’s no way we can handle this many![VAR 0114(0008)]",
  "common_1180_botan_02a": "And don’t tell me...they’re all ancient Pokémon?![VAR 0114(0008)]",
  "common_1180_botan_02b": "And don’t tell me...they’re all future Pokémon?![VAR 0114(0008)]",
  "common_1180_friend_00": "We’ve got a little disaster on our hands here...[VAR 0114(0006)]",
  "common_1180_legend_01": "Kiusss...",
  "common_1180_friend_01": "Look, even that fellow’s ready to bail...[VAR 0114(0006)]",
  "common_1180_rival_01": "Then I guess it’s my turn! I’ve been waitin’![VAR 0114(0004)]",
  "common_1180_rival_02": "[VAR BD06(0000)]C’mon, [VAR TRNAME(0000)]! Let’s do this\ntogether![VAR 0114(0004)]",
  "common_1180_rival_03": "Wow, they’re strong! Now THIS is a\nworthwhile challenge![VAR 0114(0004)]",
  "common_1180_botan_03": "I’m glad you’re on our side, but you’re still\nREALLY annoying when you say stuff like that![VAR 0114(0008)]",
  "common_1180_botan_04": "Gyah! Why’re they coming at ME?![VAR 0114(0008)]",
  "common_1180_botan_05": "[VAR TRNAME(0000)]! Help me out here![VAR 0114(0008)]",
  "common_1180_botan_06a": "Guh. The ancient past must’ve been terrifying...[VAR 0114(0008)]",
  "common_1180_botan_06b": "Guh. The future must be terrifying...[VAR 0114(0008)]",
  "common_1180_poke_01a": "Ah-GIIIAAAS!",
  "common_1180_poke_01b": "Ah-GIIIAAAS!",
  "common_1180_rival_04": "Oh no! They’re running away![VAR 0114(0004)]",
  "common_1180_botan_07": "Yeah, and?[VAR 0114(0008)]",
  "common_1180_rival_05": "If those Pokémon get out, we’re gonna have\na gigantic mess on our hands!\\c\nWe gotta go after ’em, Penny![VAR 0114(0004)]",
  "common_1180_botan_08": "Why me?![VAR 0114(0008)]",
  "common_1180_rival_06": "Waaaiiit! Hah... Hah...[VAR 0114(0004)]",
  "common_1180_rival_07": "[~ 24]",
  "common_1180_botan_09": "[~ 25]",
  "common_1180_botan_10": "Gah! Hold on, Nemona—and why do I get the\nfeeling you’re enjoying all this?![VAR 0114(0008)]",
  "common_1180_friend_02": "I hope the two of them can handle their part...[VAR 0114(0006)]",
  "common_1180_friend_03": "But at least the crowd’s been thinned out now.\nGuess it’s up to us to deal with what’s left![VAR 0114(0006)]",
  "common_1180_friend_04": "Let’s go for this strong-looking one first![VAR 0114(0006)]",
  "common_1180_friend_05": "See! The power of friendship had us perfectly\nin sync! All thanks to our Titan hunting together![VAR 0114(0006)]",
  "common_1180_legend_02": "... ... ...",
  "common_1180_friend_06": "Still scared, huh? You worried you might have to\nface that other one of your kind?[VAR 0114(0006)]",
  "common_1180_friend_07": "Well then, lemme take on some of the burden![VAR 0114(0006)]",
  "common_1180_friend_08": "These stragglers should be nothing! Me and\nMabosstiff here can take them![VAR 0114(0006)]",
  "common_1180_mastiff_01": "Bawf!",
  "common_1180_friend_09": "[VAR BD06(0000)]So, [VAR TRNAME(0000)], you take your\npartner\\r\nthere\\r\nand\\r\ngo\\r\ntake\\r\ncare\\r\nof business![VAR 0114(0006)]",
  "common_1180_select_01": "Got it!",
  "common_1180_select_02": "But...",
  "common_1180_friend_10": "Heheh, glad to see you’ve got some faith in us\nat last!\\c\nMabosstiff can’t wait to battle, either![VAR 0114(0006)]",
  "common_1180_friend_11": "Aw, come on! If you’re not even gonna rely on\nyour friends, then who are you going to rely on?\\r\nMabosstiff here is raring to go! Leave this to us![VAR 0114(0006)]",
  "common_1180_mastiff_02": "Bau-wauuuw!",
  "common_1180_friend_12": "[VAR PKNAME(0001)]![VAR 0114(0006)]",
  "common_1180_friend_13": "You really ruined my whole childhood, you know.[VAR 0114(0006)]",
  "common_1180_friend_14": "But it’s not like seeing you cowering and scared\noutta your wits makes me feel any better about it.[VAR 0114(0006)]",
  "common_1180_friend_15": "You’ve got amazing powers, if you just use ’em!\nAnd you’ve got us, too! So... So...\\c\nSo don’t you even think about losing to that jerk![VAR 0114(0006)]",
  "common_1180_friend_16": "Be brave—stand up and fight![VAR 0114(0006)]",
  "common_1180_friend_17": "[VAR BD06(0000)]Go, [VAR TRNAME(0000)]!\nWe’ll\\r\nfollow\\r\nas\\r\nsoon\\r\nas\\r\nwe can![VAR 0114(0006)]",
  "common_1180_mastiff_03": "Bauw! Bauw-wauw!",
  "common_1180_poke_02a": "Paaass!",
  "common_1180_poke_03a": "Primiii!",
  "common_1180_poke_04a": "Baigoooooone!",
  "common_1180_poke_02b": "Pi-ga-ga!",
  "common_1180_poke_03b": "Whrrr!",
  "common_1180_poke_04b": "Tekkk!",
  "common_1180_popup_01a": "Preeeeee!",
  "common_1180_popup_02a": "Grum-grum-grum-grum!",
  "common_1180_popup_03a": "Bifaaah!",
  "common_1180_popup_04a": "Dah-dah-dah!",
  "common_1180_popup_05a": "Gasss! Basss!",
  "common_1180_popup_01b": "Dee-dee-deee!",
  "common_1180_popup_02b": "Klink! Klunk!",
  "common_1180_popup_03b": "Vwooohm!",
  "common_1180_popup_04b": "Nyuuum!",
  "common_1180_popup_05b": "Bee-beeeeee!"
}