{
  "msg_ui_pokelist_00": "[~ 0]",
  "msg_ui_pokelist_01": "Which Pokémon will you swap it for?",
  "msg_ui_pokelist_08": "Which held item will you swap it for?",
  "msg_ui_pokelist_02": "[~ 3]",
  "msg_ui_pokelist_03": "[VAR BD06(0000)]You received the\n[VAR sTRBAG(0001)]\\r\nfrom [VAR PKNICK(0000)].\\c",
  "msg_ui_pokelist_04": "[VAR PKNICK(0000)] isn’t holding anything.\\c",
  "msg_ui_pokelist_05": "You can’t receive the item because your Bag\nis full.\\c",
  "msg_ui_pokelist_06": "[~ 7]",
  "msg_ui_pokelist_omakase": "Auto Battle",
  "msg_ui_pokelist_07": "[~ 9]",
  "msg_ui_pokelist_12": "[~ 10]",
  "msg_ui_pokelist_13": "Which Pokémon will you battle with?",
  "msg_ui_pokelist_14": "You can’t select an Egg.\\c",
  "msg_ui_pokelist_15": "[~ 13]",
  "msg_ui_pokelist_box": "[~ 14]",
  "msg_ui_pokelist_lv": "Lv. [VAR NUM3(0000)]",
  "msg_ui_pokelist_pokename": "[VAR PKNICK(0000)]",
  "msg_ui_pokelist_hp_00": "HP",
  "msg_ui_pokelist_hp_01": "/",
  "msg_ui_pokelist_hp_02": "[VAR NUM4(0000,0000)]",
  "msg_ui_pokelist_hp_03": "[VAR NUM4(0000,0000)]",
  "msg_ui_pokelist_hp": "[VAR NUM3(0000)]/[VAR NUM3(0001)]",
  "msg_ui_pokelist_Choice_00": "Check summary",
  "msg_ui_pokelist_Choice_01": "Restore health",
  "msg_ui_pokelist_Choice_02": "[~ 24]",
  "msg_ui_pokelist_Choice_03": "Back",
  "msg_ui_pokelist_Choice_04": "Change position",
  "msg_ui_pokelist_Choice_05": "Change held item",
  "msg_ui_pokelist_Choice_06": "Put away held item",
  "msg_ui_pokelist_Choice_07": "Give an item to hold",
  "msg_ui_pokelist_Choice_08": "Return to ride form",
  "msg_ui_pokelist_item": "[VAR ITEM2(0000)]",
  "msg_ui_pokelist_wazaoshie_00": "[~ 32]",
  "msg_ui_pokelist_wazaoshie_01": "[~ 33]",
  "msg_ui_pokelist_wazaoshie_02": "[~ 34]",
  "msg_ui_pokelist_item_Choice_00": "[~ 35]",
  "msg_ui_pokelist_item_Choice_01": "[~ 36]",
  "msg_ui_pokelist_item_Choice_02": "[~ 37]",
  "msg_ui_pokelist_item_Choice_03": "[~ 38]",
  "msg_ui_pokelist_help_00": "[~ 39]",
  "msg_ui_pokelist_help_01": "[~ 40]",
  "msg_ui_pokelist_help_02": "[~ 41]",
  "msg_ui_pokelist_help_03": "[~ 42]",
  "msg_ui_pokelist_help_04": "Quit",
  "msg_ui_pokelist_help_05": "[~ 44]",
  "msg_ui_pokelist_help_06": "Select",
  "msg_ui_pokelist_have_00": "[~ 46]",
  "msg_ui_pokelist_have_01": "[~ 47]",
  "msg_ui_pokelist_have_02": "[~ 48]",
  "msg_ui_pokelist_have_03": "[~ 49]",
  "msg_ui_pokelist_select": "[~ 50]",
  "msg_ui_pokelist_ride_off": "Get Off",
  "msg_ui_pokelist_ride_on": "Get On",
  "msg_ui_pokelist_omakase01": "[~ 53]",
  "msg_ui_pokelist_omakase02": "[~ 54]",
  "msg_ui_pokelist_omakase03": "[VAR PKNICK(0000)] isn’t nearby!\\c",
  "msg_ui_pokelist_ridepoke_01": "[VAR BD06(0000)]You can’t send [VAR PKNICK(0000)] to\nyour Boxes.\\c"
}