{
  "msg_shinka_01_01": "What? [VAR PKNICK(0000)] is evolving!",
  "msg_shinka_02_01": "Huh? [VAR PKNICK(0000)] stopped evolving!",
  "msg_shinka_03_01": "[VAR BD06(0000)]Congratulations! Your [VAR PKNICK(0000)]\nevolved\\r\ninto [VAR PKNAME(0001)]!",
  "msg_shinka_04_01": "[VAR BD06(0000)][VAR PKNICK(0000)] learned\n[VAR MOVE(0001)]![VAR BE05(0004)][VAR BE05(0001)]",
  "msg_shinka_05_01": "One...[WAIT 10]two...[WAIT 10]and...[WAIT 20]ta-da![VAR BE05(0003)][VAR BE05(0005)]\\c\n[VAR PKNICK(0000)] forgot [VAR MOVE(0002)]...\n[VAR BE05(0006)]and it learned [VAR MOVE(0001)] instead![VAR BE05(0004)]",
  "msg_shinka_06_01": "[VAR BD06(0000)][VAR PKNICK(0000)] did not learn\n[VAR MOVE(0001)].",
  "msg_shinka_07_01": "[VAR BD06(0000)][VAR PKNICK(0000)] wants to learn the\nmove\\r\n[VAR MOVE(0001)].\\c\nShould another move be forgotten and replaced\nwith [VAR MOVE(0001)]?",
  "msg_shinka_10_01": "Forget a move",
  "msg_shinka_10_02": "Keep current moves"
}